LICENSE
MANIFEST.in
README.rst
setup.py
rpi_dots_minecraft/__init__.py
rpi_dots_minecraft/dots_minecraft.py
rpi_dots_minecraft.egg-info/PKG-INFO
rpi_dots_minecraft.egg-info/SOURCES.txt
rpi_dots_minecraft.egg-info/dependency_links.txt
rpi_dots_minecraft.egg-info/requires.txt
rpi_dots_minecraft.egg-info/top_level.txt
scripts/rpi_dots_minecraft