Metadata-Version: 1.0
Name: rpi-dots-minecraft
Version: 0.1.3
Summary: A Python program that reads the selected dots on the Raspberry Pi DOTs board and uses these to generate a 3d simulated airplane inside Minecraft Pi.
Home-page: https://github.com/gbaman/rpi_dots_minecraft
Author: Andrew Mulholland
Author-email: gbaman1@gmail.com
License: MIT
Platform: UNKNOWN
